mstr_robotics/__init__.py
mstr_robotics/_connectors.py
mstr_robotics/_helper.py
mstr_robotics/_lu_data.py
mstr_robotics/_mod_prj_obj.py
mstr_robotics/dossier.py
mstr_robotics/mstr_classes.py
mstr_robotics/mstr_pandas.py
mstr_robotics/navigation.py
mstr_robotics/prepare_AI_data.py
mstr_robotics/read_out_prj_obj.py
mstr_robotics/report.py
mstr_robotics/user_RAG.py
mstr_robotics_magerdaniel-0.3.12.dist-info/licenses/LICENSE
mstr_robotics_magerdaniel-0.3.12.dist-info/METADATA
mstr_robotics_magerdaniel-0.3.12.dist-info/WHEEL
mstr_robotics_magerdaniel-0.3.12.dist-info/top_level.txt
mstr_robotics_magerdaniel-0.3.12.dist-info/RECORD
