Metadata-Version: 2.4
Name: MSTR_Robotics_magerdaniel
Version: 0.3.12
Summary: MicroStrateg(P)ython
Home-page: https://github.com/magerdaniel
Author: Daniel Mager
Author-email: danielmager@gmx.de
Classifier: Programming Language :: Python :: 3
Classifier: License :: OSI Approved :: MIT License
Classifier: Operating System :: OS Independent
Requires-Python: >=3.8
License-File: LICENSE
Requires-Dist: mstrio-py==11.4.9.101
Requires-Dist: langchain
Requires-Dist: openai
Requires-Dist: tiktoken
Requires-Dist: langchain-community
Requires-Dist: faiss-cpu
Requires-Dist: flashtext>=2.7
Dynamic: author
Dynamic: author-email
Dynamic: classifier
Dynamic: description
Dynamic: description-content-type
Dynamic: home-page
Dynamic: license-file
Dynamic: requires-dist
Dynamic: requires-python
Dynamic: summary
